pytimeir/__init__.py
pytimeir/events_extractor.py
pytimeir/main.py
pytimeir/utils.py
pytimeir-0.3.dist-info/licenses/LICENSE
pytimeir-0.3.dist-info/METADATA
pytimeir-0.3.dist-info/WHEEL
pytimeir-0.3.dist-info/top_level.txt
pytimeir-0.3.dist-info/RECORD
