Metadata-Version: 2.4
Name: pytimeir
Version: 0.3
Summary: Get events and holidays from time.ir
Home-page: https://github.com/saeedghadiri/pytimeir
Author: Saeed Ghadiri
Author-email: saeed.ghadiri@gmail.com
Project-URL: Bug Tracker, https://github.com/saeedghadiri/pytimeir/issues
Classifier: Programming Language :: Python
Classifier: Programming Language :: Python :: 3.6
Classifier: Programming Language :: Python :: 3.7
Classifier: Programming Language :: Python :: 3.8
Classifier: Programming Language :: Python :: 3.9
Classifier: Programming Language :: Python :: 3.10
Classifier: License :: OSI Approved :: MIT License
Classifier: Operating System :: OS Independent
Requires-Python: >=3.6
License-File: LICENSE
Requires-Dist: requests
Requires-Dist: pandas
Requires-Dist: jdatetime
Requires-Dist: Unidecode
Dynamic: author
Dynamic: author-email
Dynamic: classifier
Dynamic: description
Dynamic: description-content-type
Dynamic: home-page
Dynamic: license-file
Dynamic: project-url
Dynamic: requires-dist
Dynamic: requires-python
Dynamic: summary
